insult_ai/__init__.py
insult_ai/console.py
insult_ai-0.2.0.dist-info/entry_points.txt
insult_ai-0.2.0.dist-info/WHEEL
insult_ai-0.2.0.dist-info/METADATA
insult_ai-0.2.0.dist-info/RECORD
